LICENSE.txt
README.txt
setup.py
getviz/SETUP.py
getviz/__init__.py
getviz.egg-info/PKG-INFO
getviz.egg-info/SOURCES.txt
getviz.egg-info/dependency_links.txt
getviz.egg-info/requires.txt
getviz.egg-info/top_level.txt