Metadata-Version: 2.1
Name: getviz
Version: 0.0.1
Summary: VizPy is a powerful Python library designed to streamline the process of creating visually stunning and informative data visualizations.
Home-page: 
Author: Manas Parashar
Author-email: parasharmanas.2002@gmail.com
License: MIT
Classifier: Development Status :: 5 - Production/Stable
Classifier: Intended Audience :: Education
Classifier: Operating System :: Microsoft :: Windows :: Windows 10
Classifier: License :: OSI Approved :: MIT License
Classifier: Programming Language :: Python :: 3
License-File: LICENSE.txt
